lister/__init__.py
lister/main.py
files_lister-0.2.2.dist-info/METADATA
files_lister-0.2.2.dist-info/WHEEL
files_lister-0.2.2.dist-info/entry_points.txt
files_lister-0.2.2.dist-info/RECORD
