Metadata-Version: 2.4
Name: files_lister
Version: 0.2.2
Summary: A utility for recursively listing and saving the content of source code files
License-Expression: MIT
Requires-Python: >=3.9
Requires-Dist: coverage==7.6.10
Requires-Dist: flake8>=7.1.1
Requires-Dist: pytest-cov
Requires-Dist: pytest-mock>=3.14.0
Requires-Dist: pytest>=8.3.4
Requires-Dist: ruff>=0.9.2
